dar_tool/__init__.py
dar_tool/suppression_check.py
dar_tool-1.0.7.dist-info/licenses/LICENSE
test/__init__.py
test/test_data_anonymizer.py
util/LogUtil.py
util/__init__.py
dar_tool-1.0.7.dist-info/METADATA
dar_tool-1.0.7.dist-info/WHEEL
dar_tool-1.0.7.dist-info/top_level.txt
dar_tool-1.0.7.dist-info/RECORD
