Metadata-Version: 2.4
Name: dar-tool
Version: 1.0.7
Summary: A Python package for anonymizing sensitive data in pandas DataFrames.
Home-page: https://github.com/P20WCommunityOfInnovation/DisclosureAvoidance
Author: P20W+ Community of Innovation
Author-email: info@communityofinnovation.org
Keywords: data anonymization,privacy,pandas
Classifier: Development Status :: 5 - Production/Stable
Classifier: Intended Audience :: Information Technology
Classifier: Topic :: Software Development :: Libraries :: Python Modules
Classifier: License :: OSI Approved :: Apache Software License
Classifier: Programming Language :: Python :: 3
Requires-Python: >=3.10
License-File: LICENSE
Requires-Dist: pandas>=1.0.0
Dynamic: author
Dynamic: author-email
Dynamic: classifier
Dynamic: description
Dynamic: description-content-type
Dynamic: home-page
Dynamic: keywords
Dynamic: license-file
Dynamic: requires-dist
Dynamic: requires-python
Dynamic: summary
